labml_helpers/__init__.py
labml_helpers/device.py
labml_helpers/module.py
labml_helpers/optimizer.py
labml_helpers/schedule.py
labml_helpers/seed.py
labml_helpers/train_valid.py
labml_helpers/training_loop.py
labml_helpers/utils.py
labml_helpers/datasets/__init__.py
labml_helpers/datasets/cifar10.py
labml_helpers/datasets/csv.py
labml_helpers/datasets/mnist.py
labml_helpers/datasets/remote/__init__.py
labml_helpers/datasets/remote/client.py
labml_helpers/datasets/remote/server.py
labml_helpers/datasets/remote/test/__init__.py
labml_helpers/datasets/remote/test/mnist_server.py
labml_helpers/datasets/remote/test/mnist_train.py
labml_helpers/datasets/remote/test/mnist_train_normal.py
labml_helpers/datasets/text/__init__.py
labml_helpers/metrics/__init__.py
labml_helpers/metrics/accuracy.py
labml_helpers/metrics/collector.py
labml_helpers/metrics/recall_precision.py
labml_helpers/metrics/simple_state.py
labml_helpers-0.4.89.dist-info/METADATA
labml_helpers-0.4.89.dist-info/WHEEL
labml_helpers-0.4.89.dist-info/top_level.txt
labml_helpers-0.4.89.dist-info/RECORD
